{
  "guesslike": [
    {
      "img": "https://imagev2.xmcdn.com/storages/5080-audiofreehighqps/55/76/GKwRIW4Gnpv0AAKVRAF6Ypw8.jpeg!strip=1&quality=7&magick=webp&op_type=3&columns=290&rows=290",
      "author": "漓茉沫",
      "times": "13284288",
      "title": "嫡女重生之一品毒妃/古风言情/免费重生爽文",
      "vip": 0,
      "free": 0
    },
    {
      "img": "https://imagev2.xmcdn.com/storages/7eea-audiofreehighqps/AA/47/GKwRIaIG4kLxAANaLAGZUKHS.jpeg!strip=1&quality=7&magick=webp&op_type=3&columns=290&rows=290",
      "author": "新月FM",
      "times": "54395984",
      "title": "农家团宠娇娇女《免费》",
      "vip": 1,
      "free": 0
    },
    {
      "img": "https://imagev2.xmcdn.com/storages/5678-audiofreehighqps/11/64/GMCoOSUG4mB4AAPRQwGZX6Tb.jpeg!strip=1&quality=7&magick=webp&op_type=3&columns=290&rows=290",
      "author": "筱鱼er_优一剧社",
      "times": "765324323",
      "title": "离婚后，我怀了大佬的三个祖宗",
      "vip": 0,
      "free": 1
    },
    {
      "img": "https://imagev2.xmcdn.com/storages/362e-audiofreehighqps/42/DD/GMCoOScH9TlyAAHNEwIG7izF.jpeg!strip=1&quality=7&magick=webp&op_type=3&columns=290&rows=290",
      "author": "雯雯成长吧",
      "times": "674564545",
      "title": "强者思维 | 每天精进一点，用智慧助力成长",
      "vip": 0,
      "free": 0
    },
    {
      "img": "https://imagev2.xmcdn.com/storages/9258-audiofreehighqps/1A/6B/GKwRIJIJcG7gAAI09QKYB0gh.jpeg!strip=1&quality=7&magick=webp&op_type=3&columns=290&rows=290",
      "author": "少年郭",
      "times": "746523438",
      "title": "8090后经典歌曲 | 总有一首歌让你想起过去",
      "vip": 0,
      "free": 1
    },
    {
      "img": "https://imagev2.xmcdn.com/storages/71b8-audiofreehighqps/28/E0/GKwRIJEF3qL2AAMMJwEWtA3Y.jpeg!strip=1&quality=7&magick=webp&op_type=3&columns=290&rows=290",
      "author": "大睿有声",
      "times": "983543544",
      "title": "修仙太难了|最强系统|搞笑",
      "vip": 0,
      "free": 0
    },
    {
      "img": "https://imagev2.xmcdn.com/storages/316d-audiofreehighqps/9E/97/CMCoOSQDwwofAA3UPQB2uHuu.jpg!strip=1&quality=7&magick=webp&op_type=3&columns=290&rows=290",
      "author": "欢喜杰声",
      "times": "45354354",
      "title": "猎凶之无敌警探丨探案推理 抽丝剥茧（精品双播）",
      "vip": 0,
      "free": 0
    },
    {
      "img": "https://imagev2.xmcdn.com/storages/80f7-audiofreehighqps/8E/87/GKwRIUEIgo4mAAmQBwI2eT3M.jpg!strip=1&quality=7&magick=webp&op_type=3&columns=290&rows=290",
      "author": "介么好听",
      "times": "768768767",
      "title": "重生六零：军嫂有空间丨穿越年代空间文甜宠爽文",
      "vip": 1,
      "free": 0
    },
    {
      "img": "https://imagev2.xmcdn.com/storages/bfb8-audiofreehighqps/1D/EA/GKwRIJIHcdDVAAKb6AHhK9xO.jpeg!strip=1&quality=7&magick=webp&op_type=3&columns=290&rows=290",
      "author": "邮差来敲门",
      "times": "434454354",
      "title": "免费 返回1998｜重生白手起家",
      "vip": 0,
      "free": 0
    },
    {
      "img": "https://imagev2.xmcdn.com/storages/aa13-audiofreehighqps/3E/6F/GMCoOSIIgTzvAAIiPQI19M5F.jpg!strip=1&quality=7&magick=webp&op_type=3&columns=290&rows=290",
      "author": "讲故事的慕沐",
      "times": "134354436",
      "title": "太太要休夫|霸总苏撩|打脸爽文甜宠萌宝|精品多人剧",
      "vip": 1,
      "free": 0
    }
  ],
  "audiobook": {
    "toutuoyuan": [
      {
        "img": "https://imagev2.xmcdn.com/group85/M01/D4/C9/wKg5JV8iQ4mh09uqAAgNhXz6Nn8598.jpg!strip=1&quality=7&magick=webp&op_type=3&columns=290&rows=290",
        "text": "龙棺秘藏（悬疑精品多人剧丨南瓜楠少领衔）会员畅听",
        "author": "大睿有声"
      },
      {
        "img": "https://imagev2.xmcdn.com/storages/3fb5-audiofreehighqps/CD/81/GKwRIJIGB1yKAAPkPwEqoMkP.jpeg!strip=1&quality=7&magick=webp&op_type=3&columns=290&rows=290",
        "text": "穿越七零有空间｜单播",
        "author": "大睿有声"
      },
      {
        "img": "https://imagev2.xmcdn.com/group76/M02/9F/44/wKgO3l6CvVzDf2OLAARNj1mr8fU605.jpg!strip=1&quality=7&magick=webp&op_type=3&columns=290&rows=290",
        "text": "神级系统",
        "author": "少年郭"
      },
      {
        "img": "https://imagev2.xmcdn.com/group83/M09/BA/DB/wKg5HV8gA8LRtGGSAAr_VADkOJ8855.jpg!strip=1&quality=7&magick=webp&op_type=3&columns=290&rows=290",
        "text": "大相师（都市悬疑盗墓探案免费有声小说）",
        "author": "新月FM"
      },
      {
        "img": "https://imagev2.xmcdn.com/group74/M05/4F/DF/wKgO0l5Ld2DATZujABAJSt0fFjY368.jpg!strip=1&quality=7&magick=webp&op_type=3&columns=290&rows=290",
        "text": "精灵王子的时光舞步",
        "author": "欢喜杰声"
      },
      {
        "img": "https://imagev2.xmcdn.com/group87/M0A/94/1A/wKg5J18D3pPgAvrWAAOcnP_Mb08613.jpg!strip=1&quality=7&magick=webp&op_type=3&columns=290&rows=290",
        "text": "最后一个锁龙人（悬疑灵异双播）",
        "author": "漓茉沫"
      },
      {
        "img": "https://imagev2.xmcdn.com/storages/05af-audiofreehighqps/B7/17/GKwRIDoFqNJVAAQ-aQEJwtUq.jpeg!strip=1&quality=7&magick=webp&op_type=3&columns=290&rows=290",
        "text": "诡语怪谈｜民间故事档案馆",
        "author": "热剧场"
      },
      {
        "img": "https://imagev2.xmcdn.com/group72/M05/66/7C/wKgO0F4wD1TTATAMAAGrZuVcaXM082.jpg!strip=1&quality=7&magick=webp&op_type=3&columns=290&rows=290",
        "text": "神医赘婿｜妙手神医混都市｜爆爽",
        "author": "熊猫青云_云之声"
      },
      {
        "img": "https://imagev2.xmcdn.com/group86/M01/7F/8C/wKg5Jl8aWQeyrSB6AAambngUP4I20.jpeg!strip=1&quality=7&magick=webp&op_type=3&columns=290&rows=290",
        "text": "大叔，你家萌妻开挂了（女配穿书甜宠轻喜剧丨免费多人）",
        "author": "讲故事的慕沐"
      },
      {
        "img": "https://imagev2.xmcdn.com/group83/M0B/94/63/wKg5I17ocSnxvoF5AAHwTCUmQhw020.jpg!strip=1&quality=7&magick=webp&op_type=3&columns=290&rows=290",
        "text": "诡案笔录：演罪师（有声的紫襟 | 免费有声小说）",
        "author": "王明军"
      }
    ],
    "doupocangqiong": [
      {
        "img": "https://imagev2.xmcdn.com/group85/M01/D4/C9/wKg5JV8iQ4mh09uqAAgNhXz6Nn8598.jpg!strip=1&quality=7&magick=webp&op_type=3&columns=290&rows=290",
        "text": "史上最佳女婿|精品双播|整本免费",
        "author": "雯雯成长吧"
      },
      {
        "img": "https://imagev2.xmcdn.com/storages/3fb5-audiofreehighqps/CD/81/GKwRIJIGB1yKAAPkPwEqoMkP.jpeg!strip=1&quality=7&magick=webp&op_type=3&columns=290&rows=290",
        "text": "神医小毒妃第二部：废柴七小姐逆袭 免费有声小说",
        "author": "邮差来敲门"
      },
      {
        "img": "https://imagev2.xmcdn.com/group76/M02/9F/44/wKgO3l6CvVzDf2OLAARNj1mr8fU605.jpg!strip=1&quality=7&magick=webp&op_type=3&columns=290&rows=290",
        "text": "不败仙帝丨免费有声小说丨玄幻小说丨一剑独尊仙武帝尊同款",
        "author": "讲故事的慕沐"
      },
      {
        "img": "https://imagev2.xmcdn.com/storages/1b6a-audiofreehighqps/A1/A6/CMCoOScDgBbaAAOZGgBlgAIv.jpg!strip=1&quality=7&magick=webp&op_type=3&columns=290&rows=290",
        "text": "【免费有声小说】最强龙魂丨都市修真多人有声剧",
        "author": "筱鱼er_优一剧社"
      },
      {
        "img": "https://imagev2.xmcdn.com/storages/33ab-audiofreehighqps/43/4C/GMCoOSAG6zk0AANWiwGcjWq0.jpeg!strip=1&quality=7&magick=webp&op_type=3&columns=290&rows=290",
        "text": "东北乔四传",
        "author": "王明军"
      },
      {
        "img": "https://imagev2.xmcdn.com/storages/8b89-audiofreehighqps/0F/AD/CMCoOSYDvP_sAAdBSwB1Nt0q.jpg!strip=1&quality=7&magick=webp&op_type=3&columns=290&rows=290",
        "text": "【我滴神呀】我在仙界捡废品|免费有声小说|爆笑双播",
        "author": "熊猫青云_云之声"
      },
      {
        "img": "https://imagev2.xmcdn.com/storages/65af-audiofreehighqps/88/22/CKwRINsFA5y3AAgHugDeRSuB.jpg!strip=1&quality=7&magick=webp&op_type=3&columns=290&rows=290",
        "text": "狂爸归来丨免费多人有声剧",
        "author": "热剧场"
      },
      {
        "img": "https://imagev2.xmcdn.com/storages/d73a-audiofreehighqps/CD/21/CKwRIJIE-NEHAAeL9gDbE7xe.jpg!strip=1&quality=7&magick=webp&op_type=3&columns=290&rows=290",
        "text": "万界毒尊｜玄幻版赘婿（免费有声小说）",
        "author": "漓茉沫"
      },
      {
        "img": "https://imagev2.xmcdn.com/storages/027f-audiofreehighqps/93/55/CMCoOSMDtguwAAtT4wBzXkPo.jpg!strip=1&quality=7&magick=webp&op_type=3&columns=290&rows=290",
        "text": "透视小邪医（免费双播）",
        "author": "欢喜杰声"
      },
      {
        "img": "https://imagev2.xmcdn.com/storages/a7ee-audiofreehighqps/72/0A/CMCoOSEDWfR6AA5K4ABcYwo1.png!strip=1&quality=7&magick=webp&op_type=3&columns=290&rows=290",
        "text": "法医丑妃：王爷，晚上见｜穿越破案悬疑（永久免费）",
        "author": "少年郭"
      }
    ],
    "xinghancanlan": [
      {
        "img": "https://imagev2.xmcdn.com/group40/M00/83/3C/wKgJVFqnh0-yi1sCAAF5N3Qtsp8023.jpg!strip=1&quality=7&magick=webp&op_type=3&columns=290&rows=290",
        "text": "雨后花开 15个单身女人的故事",
        "author": "介么好听"
      },
      {
        "img": "https://imagev2.xmcdn.com/group43/M06/BC/79/wKgKklsU-LiShaHvAAHgskA4zso191.jpg!strip=1&quality=7&magick=webp&op_type=3&columns=290&rows=290",
        "text": "寒门贵妻：霸宠农家女",
        "author": "大睿有声"
      },
      {
        "img": "https://imagev2.xmcdn.com/group38/M07/00/A0/wKgJolphh1CgTcZzAAF0_qQ2BPg305.jpg!strip=1&quality=7&magick=webp&op_type=3&columns=290&rows=290",
        "text": "钱德勒经典推理小说：湖底女人",
        "author": "少年郭"
      },
      {
        "img": "https://imagev2.xmcdn.com/group60/M03/24/C6/wKgLb1zvTr2y5h3nAAMkI6f_N3w731.jpg!strip=1&quality=7&magick=webp&op_type=3&columns=290&rows=290",
        "text": "精要主义·张绍刚丨湛庐阅读",
        "author": "新月FM"
      },
      {
        "img": "https://imagev2.xmcdn.com/group36/M0B/14/EF/wKgJUlo81aiRCiE6AADalwHT4ho399.jpg!strip=1&quality=7&magick=webp&op_type=3&columns=290&rows=290",
        "text": "宋词一阕话古今",
        "author": "欢喜杰声"
      },
      {
        "img": "https://imagev2.xmcdn.com/group43/M05/4B/1E/wKgKklr76lPzjx6IAAJADfcReu8696.jpg!strip=1&quality=7&magick=webp&op_type=3&columns=290&rows=290",
        "text": "万古星辰诀",
        "author": "漓茉沫"
      },
      {
        "img": "https://imagev2.xmcdn.com/group43/M08/8F/64/wKgKklsjF7mQHQiQAAKG8XgeK5c320.jpg!strip=1&quality=7&magick=webp&op_type=3&columns=290&rows=290",
        "text": "呼兰河传 现代诗性小说扛鼎之作",
        "author": "熊猫青云_云之声"
      },
      {
        "img": "https://imagev2.xmcdn.com/group18/M09/0E/9C/wKgJKlrpew_T_KV_AAKGnc0DoVo820.jpg!strip=1&quality=7&magick=webp&op_type=3&columns=290&rows=290",
        "text": "卑鄙的圣人：曹操丨文涛演播",
        "author": "雯雯成长吧"
      },
      {
        "img": "https://imagev2.xmcdn.com/group41/M07/21/20/wKgJ8Vq8vw-Tjp4FAAHfERru_A4188.jpg!strip=1&quality=7&magick=webp&op_type=3&columns=290&rows=290",
        "text": "异世重生之无上巅峰",
        "author": "将军府的人"
      },
      {
        "img": "https://imagev2.xmcdn.com/group40/M0B/7D/CA/wKgJT1qnOdOxh5omAAGmsyAeCvU293.jpg!strip=1&quality=7&magick=webp&op_type=3&columns=290&rows=290",
        "text": "灵魂摆渡人",
        "author": "妍妍"
      }
    ],
    "santi": [
      {
        "img": "https://imagev2.xmcdn.com/storages/e033-audiofreehighqps/23/AE/CMCoOR4DniBOAAzoYABtaGA1.jpg!strip=1&quality=7&magick=webp&op_type=3&columns=290&rows=290",
        "text": "神王毒宠：二嫁王妃丨穿越甜宠（半纸鸿鹊&离沐寒）",
        "author": "就业发动机"
      },
      {
        "img": "https://imagev2.xmcdn.com/group88/M0B/AC/FF/wKg5CV-BLXCiCc7GAAi-KabpBiY138.jpg!strip=1&quality=7&magick=webp&op_type=3&columns=290&rows=290",
        "text": "农女有喜：夫君来种田|全本免费双播",
        "author": "浪子牛牛"
      },
      {
        "img": "https://imagev2.xmcdn.com/group84/M08/51/FB/wKg5JF8WRoWzjRBOAAMoM-HA5mM691.jpg!strip=1&quality=7&magick=webp&op_type=3&columns=290&rows=290",
        "text": "医妃独步天下|云天河/风泠/半坛醋会员畅听",
        "author": "严严"
      },
      {
        "img": "https://imagev2.xmcdn.com/group83/M0A/2B/02/wKg5I18qI-yz8xaMAA0_2UoyhGU531.jpg!strip=1&quality=7&magick=webp&op_type=3&columns=290&rows=290",
        "text": "墨少，夫人她又走了|免费|多人有声剧|言情|总裁",
        "author": "数码一品"
      },
      {
        "img": "https://s1.xmcdn.com/yx/ximalaya-web-static/last/dist/images/default-album_c73995d.jpg",
        "text": "诡事交易所（悬疑灵异丨老K演播）",
        "author": "上海滩换"
      },
      {
        "img": "https://imagev2.xmcdn.com/group82/M05/4E/77/wKg5HF8WRQiAJUeKAAn3V2n56wA219.jpg!strip=1&quality=7&magick=webp&op_type=3&columns=290&rows=290",
        "text": "终极豪婿（至尊上门女婿）会员免费畅听",
        "author": "2024零六零四"
      },
      {
        "img": "https://imagev2.xmcdn.com/storages/195f-audiofreehighqps/46/4B/CMCoOSIDgv4qAAG7ewBmUokd.jpg!strip=1&quality=7&magick=webp&op_type=3&columns=290&rows=290",
        "text": "【百大计划】道友请留步（海声&雨晴 双播）",
        "author": "十月一"
      },
      {
        "img": "https://imagev2.xmcdn.com/group84/M08/35/E2/wKg5Hl9Cit_wZ7F5AAL76f3ipPE474.jpg!strip=1&quality=7&magick=webp&op_type=3&columns=290&rows=290",
        "text": "我在火葬场做捉鬼师的那几年 | 免费新品",
        "author": "端午休休"
      },
      {
        "img": "https://imagev2.xmcdn.com/group90/M06/97/47/wKg5B1-AKZWQ3yO6AAo76u8Qy04656.jpg!strip=1&quality=7&magick=webp&op_type=3&columns=290&rows=290",
        "text": "老公大人请低调|总裁&甜宠（双播免费）",
        "author": "东方小孙"
      },
      {
        "img": "https://imagev2.xmcdn.com/group85/M07/C6/5A/wKg5H18g9T3DNI8JAAIoHSm6T_0445.jpg!strip=1&quality=7&magick=webp&op_type=3&columns=290&rows=290",
        "text": "田园悍妻种田忙|农门悍妻：捡个王爷来种田|穿越逆袭",
        "author": "大将风范"
      }
    ]
  },
  "ranking": [
    {
      "img": "https://imagev2.xmcdn.com/storages/a8ae-audiofreehighqps/2F/FE/GMCoOR4JmKjgAAQDgwKl5CBc.jpeg!strip=1&quality=7&magick=webp&op_type=5&upload_type=cover&name=web_large&device_type=ios",
      "desc": "南来北往｜白敬亭&金晨&丁勇岱主演影视同名有声剧｜《甄嬛传》导演x《闯关东》编剧新作｜央视&爱奇艺热播中｜年代家庭｜春节必听热剧场",
      "author": "热剧场"
    },
    {
      "img": "https://imagev2.xmcdn.com/storages/5324-audiofreehighqps/A2/34/GKwRIJEJerKOAANPmQKblyAL.jpeg!strip=1&quality=7&magick=webp&op_type=5&upload_type=cover&name=web_large&device_type=ios",
      "desc": "一句顶一万句 | 王明军演播 | 茅盾文学奖获奖作品 | 刘震云 | 中国人自己的《百年孤独》",
      "author": "王明军"
    },
    {
      "img": "https://imagev2.xmcdn.com/storages/186f-audiofreehighqps/D3/68/GMCoOR8JfB7yAAYsIQKcGjnG.jpg!strip=1&quality=7&magick=webp&op_type=5&upload_type=cover&name=web_large&device_type=ios",
      "desc": "人性的弱点丨卡耐基成功励志巨著丨情商口才丨人际关系",
      "author": "熊猫青云_云之声"
    },
    {
      "desc": "【白夜剧场】猎冰｜张颂文狂飙后首部电视剧｜大毒枭真实原型改编 | 艾宝良演播|缉毒犯罪"
    },
    {
      "desc": "沙丘正传丨爆更限时免费丨维伦纽瓦2024开年大片原著有声丨全六部丨昊澜演播"
    },
    {
      "desc": "《生死河》悬疑教父【蔡骏】巅峰力作丨多人剧"
    }
  ]
}